CHANGES.rst
CONTRIBUTORS.rst
MANIFEST.in
README.rst
setup.cfg
setup.py
docs/LICENSE.GPL
docs/LICENSE.rst
docs/index.rst
src/collective/__init__.py
src/collective.calltoaction.egg-info/PKG-INFO
src/collective.calltoaction.egg-info/SOURCES.txt
src/collective.calltoaction.egg-info/dependency_links.txt
src/collective.calltoaction.egg-info/entry_points.txt
src/collective.calltoaction.egg-info/namespace_packages.txt
src/collective.calltoaction.egg-info/not-zip-safe
src/collective.calltoaction.egg-info/requires.txt
src/collective.calltoaction.egg-info/top_level.txt
src/collective/calltoaction/__init__.py
src/collective/calltoaction/configure.zcml
src/collective/calltoaction/interfaces.py
src/collective/calltoaction/setuphandlers.py
src/collective/calltoaction/testing.py
src/collective/calltoaction/browser/__init__.py
src/collective/calltoaction/browser/configure.zcml
src/collective/calltoaction/browser/controlpanel.py
src/collective/calltoaction/browser/viewlet.pt
src/collective/calltoaction/browser/viewlet.py
src/collective/calltoaction/locales/collective.calltoaction.pot
src/collective/calltoaction/locales/update.sh
src/collective/calltoaction/locales/nl/LC_MESSAGES/collective.calltoaction.mo
src/collective/calltoaction/locales/nl/LC_MESSAGES/collective.calltoaction.po
src/collective/calltoaction/portlets/__init__.py
src/collective/calltoaction/portlets/calltoactionportlet.pt
src/collective/calltoaction/portlets/calltoactionportlet.py
src/collective/calltoaction/profiles/default/browserlayer.xml
src/collective/calltoaction/profiles/default/controlpanel.xml
src/collective/calltoaction/profiles/default/cssregistry.xml
src/collective/calltoaction/profiles/default/jsregistry.xml
src/collective/calltoaction/profiles/default/metadata.xml
src/collective/calltoaction/profiles/default/portlets.xml
src/collective/calltoaction/profiles/default/registry.xml
src/collective/calltoaction/profiles/testfixture/metadata.xml
src/collective/calltoaction/profiles/testfixture/portlets.xml
src/collective/calltoaction/resources/.gitkeep
src/collective/calltoaction/resources/calltoaction.css
src/collective/calltoaction/resources/calltoaction.js
src/collective/calltoaction/resources/pb_close.png
src/collective/calltoaction/template_overrides/.gitkeep
src/collective/calltoaction/tests/__init__.py
src/collective/calltoaction/tests/test_portlet.py
src/collective/calltoaction/tests/test_robot.py
